{"ICB": {"bin": "970415", "name": "VietinBank - NH TMCP Công thương Việt Nam"}, "VCB": {"bin": "970436", "name": "Vietcombank - Ngân hàng TMCP Ngoại Thương Việt Nam"}, "BIDV": {"bin": "970418", "name": "BIDV - NH TMCP Đầu tư và Phát triển Việt Nam"}, "VBA": {"bin": "970405", "name": "Agribank - NH Nông nghiệp và Phát triển Nông thôn Việt Nam"}, "OCB": {"bin": "970448", "name": "OCB - NH TMCP Phương Đông"}, "MB": {"bin": "970422", "name": "MBBank - NH TMCP Quân đội"}, "TCB": {"bin": "970407", "name": "Techcombank - NH TMCP Kỹ thương Việt Nam"}, "ACB": {"bin": "970416", "name": "ACB - NH TMCP Á Châu"}, "VPB": {"bin": "970432", "name": "VPBank - NH TMCP Việt Nam Thịnh Vượng"}, "TPB": {"bin": "970423", "name": "TPBank - NH TMCP Tiên Phong"}, "STB": {"bin": "970403", "name": "Sacombank - NH TMCP Sài Gòn Thương Tín"}, "HDB": {"bin": "970437", "name": "HDBank - NH TMCP Phát triển Thành phố Hồ Chí Minh"}, "VCCB": {"bin": "970454", "name": "VietCapitalBank - Ngân hàng TMCP Bản Việt"}, "SCB": {"bin": "970429", "name": "SCB - NH TMCP Sài Gòn"}, "VIB": {"bin": "970441", "name": "VIB - Ngân hàng TMCP Quốc tế Việt Nam"}, "SHB": {"bin": "970443", "name": "SHB - NH TMCP Sài Gòn - Hà Nội"}, "EIB": {"bin": "970431", "name": "Eximbank - NH TMCP Xuất Nhập khẩu Việt Nam"}, "MSB": {"bin": "970426", "name": "MSB - Ngân hàng TMCP Hàng Hải Việt Nam"}, "CAKE": {"bin": "546034", "name": "CAKE - TMCP Việt Nam Thịnh Vượng - NH số CAKE by VPBank"}, "Ubank": {"bin": "546035", "name": "Ubank - TMCP Việt Nam Thịnh Vượng - NH số Ubank by VPBank"}, "VTLMONEY": {"bin": "971005", "name": "ViettelMoney - Tổng Công ty Dịch vụ số Viettel - Chi nhánh tập đoàn công nghiệp viễn thông Quân Đội"}, "TIMO": {"bin": "963388", "name": "Timo - NH số Timo by Ban Viet Bank (Timo by Ban Viet Bank)"}, "VNPTMONEY": {"bin": "971011", "name": "VNPTMoney - VNPT Money"}, "SGICB": {"bin": "970400", "name": "SaigonBank - NH TMCP Sài Gòn Công Thương"}, "BAB": {"bin": "970409", "name": "BacABank - NH TMCP Bắc Á"}, "momo": {"bin": "971025", "name": "MoMo - CTCP Dịch Vụ Di Động Trực Tuyến"}, "PVDB": {"bin": "971133", "name": "PVcomBank Pay - Ngân hàng TMCP Đại Chúng Việ t Nam NH số"}, "PVCB": {"bin": "970412", "name": "PVcomBank - Ngân hàng TMCP Đại Chúng Việt Nam"}, "MBV": {"bin": "970414", "name": "MBV - NH TNHH MTV Việt Nam Hiện Đại"}, "NCB": {"bin": "970419", "name": "NCB - NH TMCP Quốc Dân"}, "SHBVN": {"bin": "970424", "name": "ShinhanBank - NH TNHH MTV Shinhan Việt Nam"}, "ABB": {"bin": "970425", "name": "ABBANK - NH TMCP An Bình"}, "VAB": {"bin": "970427", "name": "VietABank - NH TMCP Việt Á"}, "NAB": {"bin": "970428", "name": "NamABank - NH TMCP Nam Á"}, "PGB": {"bin": "970430", "name": "PGBank - NH TMCP Thịnh vượng và Phát triển"}, "VIETBANK": {"bin": "970433", "name": "VietBank - NH TMCP Việt Nam Thương Tín"}, "BVB": {"bin": "970438", "name": "BaoVietBank - NH TMCP Bảo Việt"}, "SEAB": {"bin": "970440", "name": "SeABank - Ngân hàng TMCP Đông Nam Á"}, "COOPBANK": {"bin": "970446", "name": "COOPBANK - NH Hợp tác xã Việt Nam"}, "LPB": {"bin": "970449", "name": "LPBank - NH TMCP Lộc Phát Việt Nam"}, "KLB": {"bin": "970452", "name": "KienLongBank - NH TMCP Kiên Long"}, "KBank": {"bin": "668888", "name": "KBank - NH Đại chúng TNHH Kasikornbank"}, "MAFC": {"bin": "977777", "name": "MAFC - Công ty Tài chính TNHH MTV Mirae Asset (Việt Nam) "}, "HLBVN": {"bin": "970442", "name": "HongLeong - NH TNHH MTV Hong Leong Việt Nam"}, "KEBHANAHN": {"bin": "970467", "name": "KEBHANAHN - NH KEB Hana – Chi nhánh Hà Nội"}, "KEBHANAHCM": {"bin": "970466", "name": "KEBHanaHCM - NH KEB Hana – Chi nhánh Thành phố Hồ Chí Minh"}, "CITIBANK": {"bin": "533948", "name": "Citibank - NH Citibank, N.A. - Chi nhánh Hà Nội"}, "CBB": {"bin": "970444", "name": "CBBank - NH Thương mại TNHH MTV Xây dựng Việt Nam"}, "CIMB": {"bin": "422589", "name": "CIMB - NH TNHH MTV CIMB Việt Nam"}, "DBS": {"bin": "796500", "name": "DBSBank - DBS Bank Ltd - Chi nhánh Thành phố Hồ Chí Minh"}, "Vikki": {"bin": "970406", "name": "Vikki - NH TNHH MTV Số Vikki"}, "VBSP": {"bin": "999888", "name": "VBSP - NH Chính sách Xã hội"}, "GPB": {"bin": "970408", "name": "GPBank - NH Thương mại TNHH MTV Dầu Khí Toàn Cầu"}, "KBHCM": {"bin": "970463", "name": "KookminHCM - NH Kookmin - Chi nhánh Thành phố Hồ Chí Minh"}, "KBHN": {"bin": "970462", "name": "KookminHN - NH Kookmin - Chi nhánh Hà Nội"}, "WVN": {"bin": "970457", "name": "Woori - NH TNHH MTV Woori Việt Nam"}, "VRB": {"bin": "970421", "name": "VRB - NH Liên doanh Việt - Nga"}, "HSBC": {"bin": "458761", "name": "HSBC - NH TNHH MTV HSBC (Việt Nam)"}, "IBK - HN": {"bin": "970455", "name": "IBKHN - Ngân hàng Công nghiệp Hàn Quốc - Chi nhánh Hà Nội"}, "IBK - HCM": {"bin": "970456", "name": "IBKHCM - Ngân hàng Công nghiệp Hàn Quốc - Chi nhánh TP. Hồ Chí Minh"}, "IVB": {"bin": "970434", "name": "IndovinaBank - NH TNHH Indovina"}, "UOB": {"bin": "970458", "name": "UnitedOverseas - NH United Overseas - Chi nhánh TP. Hồ Chí Minh"}, "NHB HN": {"bin": "801011", "name": "Nonghyup - NH Nonghyup - Chi nhánh Hà Nội"}, "SCVN": {"bin": "970410", "name": "StandardChartered - NH TNHH MTV Standard Chartered Bank Việt Nam"}, "PBVN": {"bin": "970439", "name": "PublicBank - NH TNHH MTV Public Việt Nam"}}
